pyldplayer/__init__.py
pyldplayer/coms/app.py
pyldplayer/coms/appattr.py
pyldplayer/coms/batchConsole.py
pyldplayer/coms/console.py
pyldplayer/enums/__init__.py
pyldplayer/enums/consoleCmds.py
pyldplayer/interfaces/console.py
pyldplayer/model/LeidianConfig.py
pyldplayer/model/LeidiansConfig.py
pyldplayer/model/kmp.py
pyldplayer/model/list2meta.py
pyldplayer/model/record.py
pyldplayer/model/smp.py
pyldplayer/utils/__init__.py
pyldplayer/utils/dotdict.py
pyldplayer/utils/query.py
pyldplayer/utils/subproc.py
pyldplayer-4.1.7.dist-info/METADATA
pyldplayer-4.1.7.dist-info/WHEEL
pyldplayer-4.1.7.dist-info/licenses/LICENSE
pyldplayer-4.1.7.dist-info/RECORD
