Metadata-Version: 2.4
Name: pyldplayer
Version: 4.1.7
Summary: python wrapper for LDPlayer with no additional dependencies
Author-email: ZackaryW <36378555+ZackaryW@users.noreply.github.com>
License-File: LICENSE
Requires-Python: >=3.8
